moustache_fusion/__init__.py
moustache_fusion/datatransfer.py
moustache_fusion/exceptions.py
moustache_fusion/logger.py
moustache_fusion/skittlesproc.py
moustache_fusion/skittlespy.py
moustache_fusion/webservice.py
moustache_fusion/static/favicon.ico
moustache_fusion/static/moustache-swap.png
moustache_fusion/templates/index.html
tests/__init__.py
tests/conftest.py
tests/helpers/__init__.py
tests/helpers/comparison.py
moustache_fusion-0.0.1.dist-info/LICENSE
moustache_fusion-0.0.1.dist-info/METADATA
moustache_fusion-0.0.1.dist-info/WHEEL
moustache_fusion-0.0.1.dist-info/entry_points.txt
moustache_fusion-0.0.1.dist-info/top_level.txt
moustache_fusion-0.0.1.dist-info/RECORD
