Metadata-Version: 2.1
Name: moustache-fusion
Version: 0.0.1
Summary: Module post-Moustache pour fusion d'annexes PDF dans PDF principal
Home-page: https://gitlab.libriciel.fr/outils/skittlespy/
Author: Libriciel SCOP
Author-email: hackathon@libriciel.coop
License: CeCILL-2.1
Platform: UNKNOWN
Classifier: Development Status :: 4 - Beta
Classifier: Environment :: Web Environment
Classifier: Framework :: Flask
Classifier: License :: OSI Approved :: CEA CNRS Inria Logiciel Libre License, version 2.1 (CeCILL-2.1)
Classifier: Operating System :: POSIX :: Linux
Classifier: Programming Language :: Python :: 3 :: Only
Classifier: Programming Language :: Python :: 3.6
Requires-Python: >=3
Requires-Dist: flask (<1.2,>=1.1)
Requires-Dist: python-magic (<0.5,>=0.4)
Requires-Dist: PyPDF2 (<1.27,>=1.26)
Requires-Dist: reportlab (<3.6,>=3.5)
Provides-Extra: dev
Requires-Dist: coverage (<5.4,>=5.3) ; extra == 'dev'
Requires-Dist: flake8 (<3.9,>=3.8) ; extra == 'dev'
Requires-Dist: pdf2image (<1.15,>=1.14) ; extra == 'dev'
Requires-Dist: pixelmatch (<0.3,>=0.2) ; extra == 'dev'
Requires-Dist: pytest (<6.2,>=6.1) ; extra == 'dev'
